digitbydigit_roots/__init__.py
digitbydigit_roots/nthroot.py
digitbydigit_roots/utils.py
digitbydigit_roots-0.1.1.dist-info/licenses/LICENSE
digitbydigit_roots-0.1.1.dist-info/METADATA
digitbydigit_roots-0.1.1.dist-info/WHEEL
digitbydigit_roots-0.1.1.dist-info/top_level.txt
digitbydigit_roots-0.1.1.dist-info/RECORD
