Metadata-Version: 2.4
Name: digitbydigit-roots
Version: 0.1.1
Summary: Exact digit-by-digit algorithms for integer nth root extraction
Author-email: Suresan Pareth <sureshpareth@gmail.com>
License: MIT
Project-URL: Homepage, https://arxiv.org/abs/2601.02703
Project-URL: Repository, https://github.com/sureshpareth/digitbydigit-roots
Requires-Python: >=3.8
License-File: LICENSE
Dynamic: license-file
